setup.py
horble_reports/__init__.py
horble_reports/horble_report.py
horble_reports.egg-info/PKG-INFO
horble_reports.egg-info/SOURCES.txt
horble_reports.egg-info/dependency_links.txt
horble_reports.egg-info/top_level.txt