Metadata-Version: 1.0
Name: horble-reports
Version: 1.0.1
Summary: Reports less horrible
Home-page: http://github.com/ccollins/horble_reports/
Author: Chuck Collins, Wilkes Joiner
Author-email: chuck.collins@gmail.com
License: MIT
Keywords: django reports
Platform: UNKNOWN
